{
  "origin": "40.743589, -73.992354",
  "destination": "40.747575, -73.988330",
  "distance": 769,
  "increment": 10,
  "points": [
    {
      "location": {
        "latitude": 40.743559361663145,
        "longitude": -73.9923105820691
      },
      "panoramaText": ["ONE", "O", "PARK", "STARBUCRS", "COFFEE", "व", "s", "PAL", "K", "生日"]
    },
    {
      "location": {
        "latitude": 40.74360128152679,
        "longitude": -73.99228008298726
      },
      "panoramaText": ["CES", "RBUCKS", "COFFEE", "Gon", "PARK"]
    },
    {
      "location": {
        "latitude": 40.743680040686684,
        "longitude": -73.9922227811052
      },
      "panoramaText": ["STARBUCKS", "COFFEE", "LLL", "CENTER", "STARBUCKS", "COFFEE", "BUROPEAN", "WAX", "CENTER", "PARKC"]
    },
    {
      "location": {
        "latitude": 40.7437587998182,
        "longitude": -73.99216547908743
      },
      "panoramaText": ["verizon", "GAOSA", "A", "CE", "RROPEAN", "WAX", "CENTER", "000", "TEEE", "EUROPEAN", "WAX", "CENTE", "EUROPEAN", "WAX", "CENTER", "verizon", "24", "ABEE"]
    },
    {
      "location": {
        "latitude": 40.74383755892143,
        "longitude": -73.99210817693393
      },
      "panoramaText": ["EUROPEAN", "AN", "WAX", "CENTER", "CYSpmacy", "Grecer", "19Chools", "CVS/pharmacy", "Grocery", "AN", "WAX", "CENTER", "BUROPEAN", "WAX", "CETER", "verzon", "STA", "PILAI"]
    },
    {
      "location": {
        "latitude": 40.74391631799631,
        "longitude": -73.99205087464473
      },
      "panoramaText": ["WHITE"]
    },
    {
      "location": {
        "latitude": 40.74399507704284,
        "longitude": -73.99199357221983
      },
      "panoramaText": ["CTS/pharmacy", "CVStarmacy", "Open", "24", "r", "ualth", "baty", "CVS/pharmacy", "Open", "24", "CTS/pharmacy", "Grocery", "ELROPE", "BEE"]
    },
    {
      "location": {
        "latitude": 40.74407383606104,
        "longitude": -73.99193626965919
      },
      "panoramaText": ["Open", "24", "H", "CVS/pharmacy", "mph", "CVS/pharmacy", "Open", "24", "Hours"]
    },
    {
      "location": {
        "latitude": 40.74415259505089,
        "longitude": -73.99187896696284
      },
      "panoramaText": ["PANGUA", "212.84.77C", "CVS/pham", "ARWAY", "FAIRWAY", "CVS/pharm", "FAWA", "Cmay"]
    },
    {
      "location": {
        "latitude": 40.74423251498623,
        "longitude": -73.99182462341078
      },
      "panoramaText": ["EWAY", "FAIRWAY", "FAIRWAY", "CVS/pham", "o", "24"]
    },
    {
      "location": {
        "latitude": 40.74431217542861,
        "longitude": -73.99176934648865
      },
      "panoramaText": ["FA", "FAIRWAY", "PAIR", "Manoma.com", "WAY", "FAIKWAY", "PATRMAY", "FAIRWAY", "CVS/hannacy", "SARE"]
    },
    {
      "location": {
        "latitude": 40.744391153498924,
        "longitude": -73.99171257209052
      },
      "panoramaText": ["FAIRWAY", "FAIKNAY", "SLAFD", "Ge", "Roco", "Menoma.com", "FAIRWAY", "FAIRWAY", "FAIRNAY", "FAIRMAY", "FAIRWAY", "G", "Diy"]
    },
    {
      "location": {
        "latitude": 40.744470131541405,
        "longitude": -73.99165579755758
      },
      "panoramaText": ["592", "FAIRWAY", "FAIRWAY", "TUM", "FATOWAY", "FAIRMAY", "FAIRMAY", "AIRWAY", "FARMA", "PAIRWAY", "QQ", "NAIL", "S", "&", "SI"]
    },
    {
      "location": {
        "latitude": 40.74454910955609,
        "longitude": -73.99159902288977
      },
      "panoramaText": ["2592", "FAIRWAY", "HIRNAY", "600", "TAIRNAY", "TRIRMAY", "THRMAY", "FAIRWAY", "SUNAC", "food", "00", "A"]
    },
    {
      "location": {
        "latitude": 40.74462808754293,
        "longitude": -73.99154224808714
      },
      "panoramaText": ["-2592", "FAIR", "FAIRWAY", "60", "THE", "H", "000", "FATRWAY", "PAIRMAY", "TAIRWAY", "TAIRNAY", "EAIRMAY", "SEPNAC", "RA73", "TUE"]
    },
    {
      "location": {
        "latitude": 40.744707065501984,
        "longitude": -73.99148547314965
      },
      "panoramaText": ["2592", "-", "WIRWAY", "FAIRWAY", "EXIT", "Menomacon", "FATR", "WAY", "TATEWAY", "FATEWAY", "PALWAY", "團"]
    },
    {
      "location": {
        "latitude": 40.744786042509176,
        "longitude": -73.99142869874159
      },
      "panoramaText": ["2592", "SInlc", "HURVAY", "FAIRE", "FABWAY", "FAIRMAY"]
    },
    {
      "location": {
        "latitude": 40.74486460419551,
        "longitude": -73.99137087994757
      },
      "panoramaText": ["af", "AI", "Bar", "picku", "AI", "Bar", "AI", "Bar"]
    },
    {
      "location": {
        "latitude": 40.74494309123023,
        "longitude": -73.99131293233853
      },
      "panoramaText": ["JA", "KOF", "FE", "CC", "FFEE", "ECAKE", "CORNIR", "E*BAKERY", "*", "DESSERT", "COFFEECAKE"]
    },
    {
      "location": {
        "latitude": 40.74502157823598,
        "longitude": -73.99125498459273
      },
      "panoramaText": ["2592", "Mo00", "henoma", "OPEN2", "His"]
    },
    {
      "location": {
        "latitude": 40.74510006521273,
        "longitude": -73.99119703671018
      },
      "panoramaText": ["2592", "Mo00", "henoma", "OPEN2", "His"]
    },
    {
      "location": {
        "latitude": 40.74517855216052,
        "longitude": -73.99113908869083
      },
      "panoramaText": ["MOME", "CHURT", "thenoma.com", "PETCST", "AVENUE"]
    },
    {
      "location": {
        "latitude": 40.74525703907931,
        "longitude": -73.99108114053469
      },
      "panoramaText": ["PET", "CENTRAL", "HOME", "CUUNT", "O", "000", "thenoma.co", "ENTRACE", "ON", "W", "27TH", "CUANEade"]
    },
    {
      "location": {
        "latitude": 40.74533552596913,
        "longitude": -73.99102319224181
      },
      "panoramaText": ["HOME", "COUR", "O", "く", "thenoma.con", "PET", "CENTEAT", "DARK", "PROENI", "O"]
    },
    {
      "location": {
        "latitude": 40.74541401282997,
        "longitude": -73.99096524381214
      },
      "panoramaText": ["COFFEE", "STARBUCH", "HOME", "COURT", "thenoha.com", "600", "SXTH"]
    },
    {
      "location": {
        "latitude": 40.7454937598672,
        "longitude": -73.99091028407842
      },
      "panoramaText": ["thenoma.com", "HSBCO", "COFFEE"]
    },
    {
      "location": {
        "latitude": 40.74557258082895,
        "longitude": -73.99085313000653
      },
      "panoramaText": ["thenoma.com", "GATABUNE", "THE", "AVIATION", "ENZY", "ANIRICAN", "BIN"]
    },
    {
      "location": {
        "latitude": 40.745651401762494,
        "longitude": -73.99079597579914
      },
      "panoramaText": ["ithenomo.com", "NYPD", "SIRTH", "CARDEN", "GOL", "JAILS", "&", "SPA"]
    },
    {
      "location": {
        "latitude": 40.745730222667845,
        "longitude": -73.99073882145629
      },
      "panoramaText": ["WALDY", "S", "NED", "thenoma.com", "WHEEECHES"]
    },
    {
      "location": {
        "latitude": 40.74580904354501,
        "longitude": -73.99068166697795
      },
      "panoramaText": ["w", "chefrwAREHOUSE", "O", "thenoma.com", "INTERN", "TIONAL", "GARDE"]
    },
    {
      "location": {
        "latitude": 40.745887864393985,
        "longitude": -73.99062451236415
      },
      "panoramaText": ["thenoma.com", "CERSPOBLS", "MAN", "EE", "ARENSON", "w", "YOR", "MEW", "NEW"]
    },
    {
      "location": {
        "latitude": 40.74596668521475,
        "longitude": -73.99056735761485
      },
      "panoramaText": ["thenoma.com"]
    },
    {
      "location": {
        "latitude": 40.74604551394759,
        "longitude": -73.9905101154127
      },
      "panoramaText": ["thenoma", "ET"]
    },
    {
      "location": {
        "latitude": 40.746123703443466,
        "longitude": -73.99045149381439
      },
      "panoramaText": ["MAA", "O", "thenoma.com", "Gigr's", "Jawolry"]
    },
    {
      "location": {
        "latitude": 40.74620189290967,
        "longitude": -73.99039287207823
      },
      "panoramaText": ["NYPD", "thenoma.om", "MAM", "staink", "Paigs", "Jewelry", "mity", "J&JN", "ADIN", "TALDALL", "NTPP"]
    },
    {
      "location": {
        "latitude": 40.74628008234622,
        "longitude": -73.99033425020423
      },
      "panoramaText": ["Pink", "lash", "M&M", "studdio", "Joweiry", "L'HIN", "TRADING", "thenoma.com", "deweiry", "Turins", "LEtermity", "JIN", "TRADING", "NYFD", "NYPD", "O"]
    },
    {
      "location": {
        "latitude": 40.7463582717531,
        "longitude": -73.99027562819236
      },
      "panoramaText": ["LMternity", "J&", "JIN", "TRAD", "NG", "Yarim", "A", "FE", "thenoma.com", "PIZZA", "Colo", "Yurim.", "OACternty", "J&", "JIN", "TRAD", "NG", "ORK", "IN", "EXPRE", "NYPD"]
    },
    {
      "location": {
        "latitude": 40.74643645882161,
        "longitude": -73.99021700382227
      },
      "panoramaText": []
    },
    {
      "location": {
        "latitude": 40.74651463433915,
        "longitude": -73.99015835048975
      },
      "panoramaText": ["FIZZA", "Clale", "Lewnny", "P", "torl", "Vers", "thenoma.con", "CEFE", "PIZZA", "Turim.", "16JIN", "日", "田", "IGS", "i", "FA"]
    },
    {
      "location": {
        "latitude": 40.74659282241289,
        "longitude": -73.9900997216175
      },
      "panoramaText": ["\"1", "PIZZA", "oma.com", "FIZZA", "Clolo", "LEL", "LAVENVELLE", "SM", "FASHION", "BEARBE", "GOURMET", "E"]
    },
    {
      "location": {
        "latitude": 40.746671374894035,
        "longitude": -73.99004144231657
      },
      "panoramaText": ["FF", "FEFE", "O", "FEFEE"]
    },
    {
      "location": {
        "latitude": 40.74675065629014,
        "longitude": -73.98998541987785
      },
      "panoramaText": ["NY", "J", "com", "FFFE", "T", "KEVITA"]
    },
    {
      "location": {
        "latitude": 40.74682993765915,
        "longitude": -73.98992939730557
      },
      "panoramaText": ["NY", "Tropicana", "adr", "tos", "NY", "J", "TE", "FERR", "FE", "EEEE", "NTPD"]
    },
    {
      "location": {
        "latitude": 40.74690921900106,
        "longitude": -73.98987337459974
      },
      "panoramaText": ["gers.", "Toese1", "Sak", "To", "NY", "J", "T", "FEEE", "ERE", "E", "EEFE", "EEEN", "E", "FREE", "FEFE"]
    },
    {
      "location": {
        "latitude": 40.746988500315894,
        "longitude": -73.98981735176032
      },
      "panoramaText": ["ALLA", "EECE", "EFERE", "LLASSIC", "NY", "THE", "INE"]
    },
    {
      "location": {
        "latitude": 40.74706778160364,
        "longitude": -73.98976132878731
      },
      "panoramaText": ["L'AMICO", "NO", "STANDIN", "Hotel", "Loading", "Zone", "Ne", "e", "IT"]
    },
    {
      "location": {
        "latitude": 40.7471470628643,
        "longitude": -73.98970530568073
      },
      "panoramaText": ["TONY"]
    },
    {
      "location": {
        "latitude": 40.74722634409786,
        "longitude": -73.98964928244057
      },
      "panoramaText": []
    },
    {
      "location": {
        "latitude": 40.74730544452978,
        "longitude": -73.98959282295611
      },
      "panoramaText": ["IN"]
    },
    {
      "location": {
        "latitude": 40.74738435719349,
        "longitude": -73.98953588721771
      },
      "panoramaText": ["UNAIRY", "PWER", "CrYCHIC", "SER", "ATPE", "NORDS", "Nordstrom", "Mens", "Store", "NYC", "NOW", "OPEN", "h", "&", "Brondvny"]
    },
    {
      "location": {
        "latitude": 40.74746326982924,
        "longitude": -73.98947895134418
      },
      "panoramaText": ["PSYCHIC", "JEWELRY", "PAIR", "NTPD", "GEAN", "IPARI", "H", "LE", "tall", "up"]
    },
    {
      "location": {
        "latitude": 40.74754218243701,
        "longitude": -73.98942201533552
      },
      "panoramaText": ["COLOEN", "AUES", "PHCHC", "SODY&", "FOCERUR", "AUXILIARY", "GoURTESY"]
    },
    {
      "location": {
        "latitude": 40.74762109501678,
        "longitude": -73.98936507919176
      },
      "panoramaText": ["MAK", "ACCESSORE", "CA", "SER", "SPA", "BARBER", "UNYPD", "IH", "H", "I", "IN", "Costunr", "国"]
    },
    {
      "location": {
        "latitude": 40.74770001552115,
        "longitude": -73.9893081625194
      },
      "panoramaText": ["LA", "SER", "SPA", "IN", "FINTY", "GRANI", "131", "LMA", "Ready", "Refres", "JUST", "CLICK", "AND", "QUENCH", "BY", "oayRefresh.C"]
    },
    {
      "location": {
        "latitude": 40.7477789242865,
        "longitude": -73.98925121656171
      },
      "panoramaText": ["IN", "FINI", "TY", "ODYA", "FO", "TRUS", "GVANI", "SYPD", "NYPD", "Readyltateshtor", "HEW", "YORK.", "LET'S", "DO", "LUNCH"]
    },
    {
      "location": {
        "latitude": 40.74785783476497,
        "longitude": -73.98919427512234
      },
      "panoramaText": ["HODY", "&", "FOOT", "ElogrS", "COFFEE", "VAy", "SZH", "VATY", "RN", "EN"]
    },
    {
      "location": {
        "latitude": 40.74793733550267,
        "longitude": -73.98913885348182
      },
      "panoramaText": ["199", "GREGORYS", "COFFEE", "ROC", "GREEORYS", "COE"]
    },
    {
      "location": {
        "latitude": 40.74801733859012,
        "longitude": -73.98908463464673
      },
      "panoramaText": ["200", "EMLLLO", "GF", "11111", "[||||||", "TBASLEY", "CO", "PSTAMDUCKS", "EGORYS", "COFFEE"]
    },
    {
      "location": {
        "latitude": 40.7480973416522,
        "longitude": -73.98903041568117
      },
      "panoramaText": ["200", "EMLLLO", "GF", "11111", "[||||||", "TBASLEY", "CO", "PSTAMDUCKS", "EGORYS", "COFFEE"]
    },
    {
      "location": {
        "latitude": 40.7481773446889,
        "longitude": -73.98897619658516
      },
      "panoramaText": ["EULL", "E", "Loved", "for", "transparency", "RAND", "OP", "A", "SP", "EULL", "N26", "Loved", "for", "transparency", "M", "Spirits", "LI", "I", "I", "W"]
    },
    {
      "location": {
        "latitude": 40.74825734770023,
        "longitude": -73.9889219773587
      },
      "panoramaText": ["FEFA", "EEE", "FFE", "NYG", "ET", "4396", "ew", "York", "Cty", "tus", "GRAND", "GP", "EMA", "NY", "GS", "4396", "N26", "Loved", "for", "transparency", "Neen", "EE", "E"]
    },
    {
      "location": {
        "latitude": 40.7483373506862,
        "longitude": -73.98886775800177
      },
      "panoramaText": ["EEE", "EE", "JORGZA", "STREE", "NY", "GF", "S", "LL", "YONE", "KANG", "STREET", "GRANTOP", "Che", "NY", "GFS", "RMONDE", "TD"]
    },
    {
      "location": {
        "latitude": 40.74841735364679,
        "longitude": -73.98881353851438
      },
      "panoramaText": [
        "CNassic",
        "Family",
        "Size",
        "lays",
        "lays",
        "s",
        "Lays",
        "s",
        "Lays",
        "ays",
        "Ligratly",
        "Salto",
        "Fami",
        "Se",
        "Pamily",
        "SE",
        "OR",
        "Dorite",
        "Dorit",
        "ay's",
        "lays",
        "Bete",
        "Hrate",
        "ice",
        "aus",
        "Lays",
        "3.49",
        "Barbecue",
        "amily",
        "S",
        "beer"
      ]
    },
    {
      "location": {
        "latitude": 40.748526600000005,
        "longitude": -73.9887395
      },
      "panoramaText": []
    },
    {
      "location": {
        "latitude": 40.748501577115114,
        "longitude": -73.98867924100232
      },
      "panoramaText": [
        "West",
        "32",
        "s",
        "The",
        "Harold.",
        "800",
        "560",
        "1165",
        "DIAMONDS",
        "&",
        "DIALS",
        "nyaWatch",
        "Experts",
        "NEW",
        "I",
        "SALE",
        "SO",
        "A",
        "ALL",
        "N",
        "N",
        "West",
        "32",
        "St",
        "DIAMONDS",
        "&",
        "DIALS",
        "For",
        "Jowin",
        "&",
        "Wabtm"
      ]
    },
    {
      "location": {
        "latitude": 40.748458351675595,
        "longitude": -73.98857514770734
      },
      "panoramaText": ["TIKET", "brunch", "Suner", "Che", "Harold", "DIAMONDS&", "DIALS", "an", "smicen", "bi", "1104"]
    },
    {
      "location": {
        "latitude": 40.74841512573482,
        "longitude": -73.98847105356577
      },
      "panoramaText": [
        "Greeley",
        "Square",
        "CHASE",
        "HASE",
        "wARTINaRIT",
        "CALE",
        "ONE",
        "WAY",
        "Dallas",
        "Plummer",
        "Greeley",
        "Square",
        "TM",
        "MARTINOUL",
        "CAFE",
        "Dallas",
        "Plummer",
        "Radissen",
        "0000",
        "著",
        "E.",
        "PEEDY'S",
        "The",
        "Harold",
        "OSADNES",
        "Dallas",
        "Plummer"
      ]
    },
    {
      "location": {
        "latitude": 40.748373610821474,
        "longitude": -73.98836578791509
      },
      "panoramaText": [
        "eat",
        "MusIc",
        "TICKE",
        "West",
        "12",
        "CHASE",
        "O",
        "TE",
        "SPEEDY'S",
        "Everyday",
        "wAT",
        "AL",
        "日",
        "EB",
        "Travelex",
        "becakfast",
        "The",
        "Harola",
        "Curreney",
        "Eschange",
        "rrency",
        "Exchengu"
      ]
    },
    {
      "location": {
        "latitude": 40.74833253129487,
        "longitude": -73.98826021274472
      },
      "panoramaText": ["श", "Surreal", "Street", "View", "000000", "Surreal", "Street", "View", "BLACK-NY", "Surreal", "Street", "View", "03.31.18", "BLACK-AVC.COM"]
    },
    {
      "location": {
        "latitude": 40.74827292742185,
        "longitude": -73.98819789722542
      },
      "panoramaText": ["CHASE", "O", "CHASEO", "CHAGE", "IONY", "GI", "Boathwty", "Catei", "PEYS", "Eveyday", "SPELD", "S", "2BHL", "AH", "HEEE"]
    },
    {
      "location": {
        "latitude": 40.74818490464368,
        "longitude": -73.98822184126047
      },
      "panoramaText": [
        "32",
        "St",
        "HING",
        "CHASE",
        "2",
        "SPEEDY",
        "ONY",
        "GIFTS",
        "E",
        "Iner",
        "Cateriya",
        "eat",
        "Lurnch",
        "TOUR",
        "SPECALISTS",
        "IN",
        "INTER",
        "NA",
        "v00",
        "CALL",
        "DwL",
        "USDOT",
        "315026"
      ]
    },
    {
      "location": {
        "latitude": 40.74809635353714,
        "longitude": -73.98824482901182
      },
      "panoramaText": ["CAL", "UME", "JAPANESE", "&K", "IONY", "GIFTS", "JME", "TRCK"]
    },
    {
      "location": {
        "latitude": 40.748007459582624,
        "longitude": -73.98826272052793
      },
      "panoramaText": ["$6", "107", "T", "P", "PERFUIE", "PRRINGS", "PLAZA", "BRIA", "AonERYECESSO", "ES", "Carsegie", "Vales"]
    },
    {
      "location": {
        "latitude": 40.747918565625326,
        "longitude": -73.98828061199623
      },
      "panoramaText": ["NOMAD", "TEWER", "435.463", "SQ", "FT.", "BEE", "NMAO", "TOWER", "435.468", "S0", "FT", "$6", "1251", "FROADWAY", "PRIME", "RETAIL", "IOPPORTUNITY"]
    },
    {
      "location": {
        "latitude": 40.74782967166527,
        "longitude": -73.9882985034167
      },
      "panoramaText": [
        "NEOMAD",
        "AD",
        "WER",
        "435.468",
        "SO",
        "FT",
        "elly",
        "CUICK",
        "BITE",
        "LLC",
        "20",
        "13",
        "24TH",
        "ST.",
        "LICNY",
        "1",
        "NO",
        "MAD",
        "TWER",
        "NIMAN",
        "435,468",
        "SQ",
        "FT",
        "inely",
        "onnelly",
        "MECMAMCAL",
        "Vww.a",
        "718-886-1900",
        "ICK",
        "BITE",
        "LLC",
        "13",
        "24TH",
        "ST.",
        "I.C",
        "NY",
        "11101",
        "KONE",
        "Elevators",
        "Eacalators"
      ]
    },
    {
      "location": {
        "latitude": 40.747740777702454,
        "longitude": -73.98831639478932
      },
      "panoramaText": ["NUVAD", "PEMER", "MAD", "TOWER", "415", "46E", "50", "FT", "128", "Bcale", "Q", "FT.", "LE", "HECIO", "TINNESEE", "DISPRUTA", "NEWNYC", "St", "E", "SE", "I"]
    },
    {
      "location": {
        "latitude": 40.74765188373688,
        "longitude": -73.98833428611412
      },
      "panoramaText": ["NUMAD", "NOMAD", "ttbike", "tubE"]
    }
  ],
  "waypoints": [],
  "options": ["panoramaText"]
}
